hashCrack/__init__.py
hashCrack/functions.py
hashCrack/hashCrack.py
hashCrack/linux_inputs.py
hashCrack/windows_inputs.py
hashCrack/linux/__init__.py
hashCrack/linux/crack_bruteforce.py
hashCrack/linux/crack_combo.py
hashCrack/linux/crack_rule.py
hashCrack/linux/crack_wordlist.py
hashCrack/windows/__init__.py
hashCrack/windows/crack_bruteforce.py
hashCrack/windows/crack_combo.py
hashCrack/windows/crack_rule.py
hashCrack/windows/crack_wordlist.py
hashcrack_tool-1.4.30.dist-info/licenses/LICENSE
hashcrack_tool-1.4.30.dist-info/METADATA
hashcrack_tool-1.4.30.dist-info/WHEEL
hashcrack_tool-1.4.30.dist-info/entry_points.txt
hashcrack_tool-1.4.30.dist-info/top_level.txt
hashcrack_tool-1.4.30.dist-info/RECORD
