Metadata-Version: 2.4
Name: hashcrack-tool
Version: 1.4.30
Summary: A tool for cracking any hash supported by Hashcat
Author: ente0
Author-email: enteo.dev@protonmail.com
License:                     GNU GENERAL PUBLIC LICENSE
Project-URL: Homepage, https://github.com/ente0/hashCrack
Project-URL: Issues, https://github.com/ente0/hashCrack/issues
Keywords: hash cracking,password cracking,hashcat
Requires-Python: >=3.6
License-File: LICENSE
Requires-Dist: termcolor
Requires-Dist: importlib-resources; python_version < "3.9"
Dynamic: license-file
